Metadata-Version: 2.4
Name: rgevolve.wet_4.jms
Version: 0.1.1
Summary: Package providing Renormalization Group Evolution Matrices for the WET-4 in the JMS basis
Author-email: Aleks Smolkovič <aleks.smolkovic@ijs.si>, Peter Stangl <peter.stangl@cern.ch>
License: MIT
Requires-Python: >=3.8
License-File: LICENSE
Requires-Dist: rgevolve-core
Dynamic: license-file
